SHA256top.v
// SHA256top.v - Consolidated and Working SHA-256 implementation
// Single file containing all SHA-256 functionality 
// NIST FIPS 180-4 Compliant - Simplified correct implementation
// Created by consolidating multiple modules into one file for easier control

module SHA256top(
    input wire clk,
    input wire reset,              // Active low reset
    input wire start_in,
    
    // Input message words W[0] to W[15] (512-bit message block)
    input wire [31:0] w0_sha256, w1_sha256, w2_sha256, w3_sha256,
    input wire [31:0] w4_sha256, w5_sha256, w6_sha256, w7_sha256,
    input wire [31:0] w8_sha256, w9_sha256, w10_sha256, w11_sha256,
    input wire [31:0] w12_sha256, w13_sha256, w14_sha256, w15_sha256,
    
    // Initial hash values (SHA-256 constants if not provided)
    input wire [31:0] A_i, B_i, C_i, D_i, E_i, F_i, G_i, H_i,
    
    // Outputs
    output reg [255:0] sha256_result,
    output reg sha256_done
);

    // SHA-256 initial hash values (NIST FIPS 180-4)
    parameter [31:0] H0_INIT = 32'h6A09E667;
    parameter [31:0] H1_INIT = 32'hBB67AE85;
    parameter [31:0] H2_INIT = 32'h3C6EF372;
    parameter [31:0] H3_INIT = 32'hA54FF53A;
    parameter [31:0] H4_INIT = 32'h510E527F;
    parameter [31:0] H5_INIT = 32'h9B05688C;
    parameter [31:0] H6_INIT = 32'h1F83D9AB;
    parameter [31:0] H7_INIT = 32'h5BE0CD19;
    
    // K constants array - NIST FIPS 180-4 compliant
    reg [31:0] K [0:63];
    initial begin
        K[0]  = 32'h428a2f98; K[1]  = 32'h71374491; K[2]  = 32'hb5c0fbcf; K[3]  = 32'he9b5dba5;
        K[4]  = 32'h3956c25b; K[5]  = 32'h59f111f1; K[6]  = 32'h923f82a4; K[7]  = 32'hab1c5ed5;
        K[8]  = 32'hd807aa98; K[9]  = 32'h12835b01; K[10] = 32'h243185be; K[11] = 32'h550c7dc3;
        K[12] = 32'h72be5d74; K[13] = 32'h80deb1fe; K[14] = 32'h9bdc06a7; K[15] = 32'hc19bf174;
        K[16] = 32'he49b69c1; K[17] = 32'hefbe4786; K[18] = 32'h0fc19dc6; K[19] = 32'h240ca1cc;
        K[20] = 32'h2de92c6f; K[21] = 32'h4a7484aa; K[22] = 32'h5cb0a9dc; K[23] = 32'h76f988da;
        K[24] = 32'h983e5152; K[25] = 32'ha831c66d; K[26] = 32'hb00327c8; K[27] = 32'hbf597fc7;
        K[28] = 32'hc6e00bf3; K[29] = 32'hd5a79147; K[30] = 32'h06ca6351; K[31] = 32'h14292967;
        K[32] = 32'h27b70a85; K[33] = 32'h2e1b2138; K[34] = 32'h4d2c6dfc; K[35] = 32'h53380d13;
        K[36] = 32'h650a7354; K[37] = 32'h766a0abb; K[38] = 32'h81c2c92e; K[39] = 32'h92722c85;
        K[40] = 32'ha2bfe8a1; K[41] = 32'ha81a664b; K[42] = 32'hc24b8b70; K[43] = 32'hc76c51a3;
        K[44] = 32'hd192e819; K[45] = 32'hd6990624; K[46] = 32'hf40e3585; K[47] = 32'h106aa070;
        K[48] = 32'h19a4c116; K[49] = 32'h1e376c08; K[50] = 32'h2748774c; K[51] = 32'h34b0bcb5;
        K[52] = 32'h391c0cb3; K[53] = 32'h4ed8aa4a; K[54] = 32'h5b9cca4f; K[55] = 32'h682e6ff3;
        K[56] = 32'h748f82ee; K[57] = 32'h78a5636f; K[58] = 32'h84c87814; K[59] = 32'h8cc70208;
        K[60] = 32'h90befffa; K[61] = 32'ha4506ceb; K[62] = 32'hbef9a3f7; K[63] = 32'hc67178f2;
    end
    
    // Right rotate function
    function [31:0] rotr;
        input [31:0] x;
        input [4:0] n;
        begin
            rotr = (x >> n) | (x << (32 - n));
        end
    endfunction
    
    // SHA-256 function definitions (inline implementations)
    
    // Choice function: Ch(e, f, g) = (e & f) ^ (~e & g)
    function [31:0] choice;
        input [31:0] e, f, g;
        begin
            choice = (e & f) ^ (~e & g);
        end
    endfunction
    
    // Majority function: Maj(a, b, c) = (a & b) ^ (a & c) ^ (b & c)
    function [31:0] majority;
        input [31:0] a, b, c;
        begin
            majority = (a & b) ^ (a & c) ^ (b & c);
        end
    endfunction
    
    // Σ₀(x) = ROTR²(x) ⊕ ROTR¹³(x) ⊕ ROTR²²(x) - for compression function
    function [31:0] big_sigma0;
        input [31:0] x;
        begin
            big_sigma0 = rotr(x, 2) ^ rotr(x, 13) ^ rotr(x, 22);
        end
    endfunction
    
    // Σ₁(x) = ROTR⁶(x) ⊕ ROTR¹¹(x) ⊕ ROTR²⁵(x) - for compression function
    function [31:0] big_sigma1;
        input [31:0] x;
        begin
            big_sigma1 = rotr(x, 6) ^ rotr(x, 11) ^ rotr(x, 25);
        end
    endfunction
    
    // σ₀(x) = ROTR⁷(x) ⊕ ROTR¹⁸(x) ⊕ SHR³(x) - for message schedule
    function [31:0] small_sigma0;
        input [31:0] x;
        begin
            small_sigma0 = rotr(x, 7) ^ rotr(x, 18) ^ (x >> 3);
        end
    endfunction
    
    // σ₁(x) = ROTR¹⁷(x) ⊕ ROTR¹⁹(x) ⊕ SHR¹⁰(x) - for message schedule
    function [31:0] small_sigma1;
        input [31:0] x;
        begin
            small_sigma1 = rotr(x, 17) ^ rotr(x, 19) ^ (x >> 10);
        end
    endfunction
    
    // State machine
    parameter [2:0] IDLE = 3'b000,
                    INIT = 3'b001,
                    PROCESS = 3'b010,
                    FINALIZE = 3'b011,
                    DONE = 3'b100;
    
    reg [2:0] state;
    reg [6:0] round_counter;  // 0-63 for SHA-256 rounds
    
    // Working variables and hash values
    reg [31:0] a, b, c, d, e, f, g, h;          // Working variables
    reg [31:0] H0, H1, H2, H3, H4, H5, H6, H7;  // Hash values
    reg [31:0] W [0:63];                        // Message schedule
    reg [31:0] W_current;                       // Current W value to avoid race conditions
    
    // Intermediate computation values
    wire [31:0] T1, T2;
    
    // Compute T1 and T2 combinationally using current W value
    assign T1 = h + big_sigma1(e) + choice(e, f, g) + K[round_counter] + W_current;
    assign T2 = big_sigma0(a) + majority(a, b, c);
    
    // State machine logic
    always @(posedge clk or negedge reset) begin
        if (!reset) begin
            state <= IDLE;
            round_counter <= 0;
            sha256_done <= 0;
            sha256_result <= 256'h0;
            W_current <= 0;
            
            // Reset working variables
            a <= 0; b <= 0; c <= 0; d <= 0; e <= 0; f <= 0; g <= 0; h <= 0;
            H0 <= 0; H1 <= 0; H2 <= 0; H3 <= 0; H4 <= 0; H5 <= 0; H6 <= 0; H7 <= 0;
            
        end else begin
            case (state)
                IDLE: begin
                    sha256_done <= 0;
                    if (start_in) begin
                        state <= INIT;
                        round_counter <= 0;
                    end
                end
                
                INIT: begin
                    // Store initial hash values for final addition
                    H0 <= H0_INIT;
                    H1 <= H1_INIT;
                    H2 <= H2_INIT;
                    H3 <= H3_INIT;
                    H4 <= H4_INIT;
                    H5 <= H5_INIT;
                    H6 <= H6_INIT;
                    H7 <= H7_INIT;
                    
                    // Initialize working variables with initial hash values
                    a <= H0_INIT;
                    b <= H1_INIT;
                    c <= H2_INIT;
                    d <= H3_INIT;
                    e <= H4_INIT;
                    f <= H5_INIT;
                    g <= H6_INIT;
                    h <= H7_INIT;
                    
                    // Initialize first 16 words of message schedule
                    W[0]  <= w0_sha256;  W[1]  <= w1_sha256;  W[2]  <= w2_sha256;  W[3]  <= w3_sha256;
                    W[4]  <= w4_sha256;  W[5]  <= w5_sha256;  W[6]  <= w6_sha256;  W[7]  <= w7_sha256;
                    W[8]  <= w8_sha256;  W[9]  <= w9_sha256;  W[10] <= w10_sha256; W[11] <= w11_sha256;
                    W[12] <= w12_sha256; W[13] <= w13_sha256; W[14] <= w14_sha256; W[15] <= w15_sha256;
                    
                    // Set current W for round 0
                    W_current <= w0_sha256;
                    
                    state <= PROCESS;
                end
                
                PROCESS: begin
                    if (round_counter < 64) begin
                        // Perform SHA-256 compression round using stable W_current
                        h <= g;
                        g <= f;
                        f <= e;
                        e <= d + T1;
                        d <= c;
                        c <= b;
                        b <= a;
                        a <= T1 + T2;
                        
                        // Increment round counter
                        round_counter <= round_counter + 1;
                        
                        // Extend message schedule and set W_current for NEXT round
                        if (round_counter < 63) begin
                            if (round_counter >= 15) begin
                                // For rounds 16-63, extend the message schedule
                                // W[t] = σ₁(W[t-2]) + W[t-7] + σ₀(W[t-15]) + W[t-16]
                                // Since we're preparing for next round (round_counter+1), compute W[round_counter+1]
                                W[round_counter+1] <= small_sigma1(W[round_counter-1]) + W[round_counter-6] + 
                                                     small_sigma0(W[round_counter-14]) + W[round_counter-15];
                                W_current <= small_sigma1(W[round_counter-1]) + W[round_counter-6] + 
                                            small_sigma0(W[round_counter-14]) + W[round_counter-15];
                            end else begin
                                // For rounds 0-15, use pre-loaded W values
                                W_current <= W[round_counter+1];
                            end
                        end
                    end else begin
                        state <= FINALIZE;
                    end
                end
                
                FINALIZE: begin
                    // Add working variables to hash values (final step)
                    H0 <= H0 + a;
                    H1 <= H1 + b;
                    H2 <= H2 + c;
                    H3 <= H3 + d;
                    H4 <= H4 + e;
                    H5 <= H5 + f;
                    H6 <= H6 + g;
                    H7 <= H7 + h;
                    
                    state <= DONE;
                end
                
                DONE: begin
                    sha256_result <= {H0, H1, H2, H3, H4, H5, H6, H7};
                    sha256_done <= 1;
                    
                    if (!start_in) begin
                        state <= IDLE;
                    end
                end
                
                default: state <= IDLE;
            endcase
        end
    end

endmodule

SHA256tb.v
`timescale 1ns / 1ps

// SHA256tb.v - Consolidated testbench for SHA-256 implementation
// Tests multiple SHA-256 test vectors to ensure correctness
// Consolidated from multiple testbench files for easier control

module SHA256tb();

    // Test bench signals
    reg clk;
    reg reset;
    reg start_in;
    
    // Input message words (512-bit block)
    reg [31:0] w0_sha256, w1_sha256, w2_sha256, w3_sha256;
    reg [31:0] w4_sha256, w5_sha256, w6_sha256, w7_sha256;
    reg [31:0] w8_sha256, w9_sha256, w10_sha256, w11_sha256;
    reg [31:0] w12_sha256, w13_sha256, w14_sha256, w15_sha256;
    
    // Initial hash values (SHA-256 constants)
    reg [31:0] A_i, B_i, C_i, D_i, E_i, F_i, G_i, H_i;
    
    // Outputs
    wire [255:0] sha256_result;
    wire sha256_done;
    
    // Expected result for comparison
    reg [255:0] expected_result;
    
    // Test result tracking
    integer passed_tests = 0;
    integer total_tests = 0;
    
    // Instantiate the consolidated SHA-256 module
    SHA256top uut (
        .clk(clk),
        .reset(reset),
        .start_in(start_in),
        
        // Input message
        .w0_sha256(w0_sha256), .w1_sha256(w1_sha256), .w2_sha256(w2_sha256), .w3_sha256(w3_sha256),
        .w4_sha256(w4_sha256), .w5_sha256(w5_sha256), .w6_sha256(w6_sha256), .w7_sha256(w7_sha256),
        .w8_sha256(w8_sha256), .w9_sha256(w9_sha256), .w10_sha256(w10_sha256), .w11_sha256(w11_sha256),
        .w12_sha256(w12_sha256), .w13_sha256(w13_sha256), .w14_sha256(w14_sha256), .w15_sha256(w15_sha256),
        
        // Initial hash values
        .A_i(A_i), .B_i(B_i), .C_i(C_i), .D_i(D_i),
        .E_i(E_i), .F_i(F_i), .G_i(G_i), .H_i(H_i),
        
        // Outputs
        .sha256_result(sha256_result),
        .sha256_done(sha256_done)
    );
    
    // Clock generation
    always begin
        clk = 0;
        #5;
        clk = 1;
        #5;
    end
    
    // Test counter for debugging
    integer cycle_count = 0;
    always @(posedge clk) begin
        if (start_in && !sha256_done) begin
            cycle_count = cycle_count + 1;
        end else if (!start_in) begin
            cycle_count = 0;
        end
    end
    
    // Task to run a single test case
    task run_test;
        input [8*50:1] test_name;
        input [255:0] expected;
        begin
            total_tests = total_tests + 1;
            cycle_count = 0;
            expected_result = expected;
            
            $display("\n=== %s ===", test_name);
            $display("W0=%08h W1=%08h W2=%08h W3=%08h", w0_sha256, w1_sha256, w2_sha256, w3_sha256);
            $display("W15=%08h (length)", w15_sha256);
            
            // Start SHA-256 computation
            start_in = 1;
            $display("Time: %0t | Starting SHA-256 computation...", $time);
            
            // Wait for computation to complete
            wait(sha256_done == 1);
            $display("Time: %0t | SHA-256 computation completed!", $time);
            $display("Cycles taken: %0d", cycle_count);
            
            // Display results
            $display("Result   : %064h", sha256_result);
            $display("Expected : %064h", expected_result);
            
            if (sha256_result == expected_result) begin
                $display("✓ %s PASSED!", test_name);
                passed_tests = passed_tests + 1;
            end else begin
                $display("✗ %s FAILED!", test_name);
                $display("  Difference found in hash computation");
            end
            
            // Stop start signal and wait
            start_in = 0;
            
            // Wait for sha256_done to go low before next test
            wait(sha256_done == 0);
            #20;
        end
    endtask
    
    // Task to clear message words
    task clear_message;
        begin
            w0_sha256 = 32'h00000000; w1_sha256 = 32'h00000000; w2_sha256 = 32'h00000000; w3_sha256 = 32'h00000000;
            w4_sha256 = 32'h00000000; w5_sha256 = 32'h00000000; w6_sha256 = 32'h00000000; w7_sha256 = 32'h00000000;
            w8_sha256 = 32'h00000000; w9_sha256 = 32'h00000000; w10_sha256 = 32'h00000000; w11_sha256 = 32'h00000000;
            w12_sha256 = 32'h00000000; w13_sha256 = 32'h00000000; w14_sha256 = 32'h00000000; w15_sha256 = 32'h00000000;
        end
    endtask
    
    initial begin
        // Initialize VCD dump
        $dumpfile("sha256_test.vcd");
        $dumpvars(0, SHA256tb);
        
        // Initialize all inputs
        reset = 0;
        start_in = 0;
        clear_message();
        
        // Initialize with SHA-256 initial hash values (use 0 to trigger defaults)
        A_i = 32'h0; B_i = 32'h0; C_i = 32'h0; D_i = 32'h0;
        E_i = 32'h0; F_i = 32'h0; G_i = 32'h0; H_i = 32'h0;
        
        // Apply reset
        $display("=== Consolidated SHA-256 Test Bench Started ===");
        $display("Time: %0t | Applying reset...", $time);
        #10;
        reset = 1;
        #20;
        
        //========================================================================
        // Test Case 1: "abc" message
        // Expected: ba7816bf8f01cfea414140de5dae2223b00361a396177a9cb410ff61f20015ad
        //========================================================================
        clear_message();
        w0_sha256 = 32'h61626380;  // "abc" + padding bit
        w15_sha256 = 32'h00000018;  // Length: 24 bits (3 bytes)
        
        run_test("Test Case 1: Message 'abc'", 
                 256'hba7816bf8f01cfea414140de5dae2223b00361a396177a9cb410ff61f20015ad);
        
        //========================================================================
        // Test Case 2: "hello world" message  
        // Expected: b94d27b9934d3e08a52e52d7da7dabfac484efe37a5380ee9088f7ace2efcde9
        //========================================================================
        clear_message();
        w0_sha256 = 32'h68656C6C;  // "hell"
        w1_sha256 = 32'h6F20776F;  // "o wo"  
        w2_sha256 = 32'h726C6480;  // "rld" + padding bit
        w15_sha256 = 32'h00000058;  // Length: 88 bits (11 bytes)
        
        run_test("Test Case 2: Message 'hello world'", 
                 256'hb94d27b9934d3e08a52e52d7da7dabfac484efe37a5380ee9088f7ace2efcde9);
        
        //========================================================================
        // Test Case 3: Empty string "" 
        // Expected: e3b0c44298fc1c149afbf4c8996fb92427ae41e4649b934ca495991b7852b855
        //========================================================================
        clear_message();
        w0_sha256 = 32'h80000000;  // Just padding bit at the beginning
        w15_sha256 = 32'h00000000;  // Length: 0 bits (0 bytes)
        
        run_test("Test Case 3: Empty string", 
                 256'he3b0c44298fc1c149afbf4c8996fb92427ae41e4649b934ca495991b7852b855);
        
        //========================================================================
        // Test Case 4: "a" message
        // Expected: ca978112ca1bbdcafac231b39a23dc4da786eff8147c4e72b9807785afee48bb
        //========================================================================
        clear_message();
        w0_sha256 = 32'h61800000;  // "a" + padding bit
        w15_sha256 = 32'h00000008;  // Length: 8 bits (1 byte)
        
        run_test("Test Case 4: Message 'a'", 
                 256'hca978112ca1bbdcafac231b39a23dc4da786eff8147c4e72b9807785afee48bb);
        
        //========================================================================
        // Test Case 5: "message digest" 
        // Expected: f7846f55cf23e14eebeab5b4e1550cad5b509e3348fbc4efa3a1413d393cb650
        //========================================================================
        clear_message();
        w0_sha256 = 32'h6D657373;  // "mess"
        w1_sha256 = 32'h61676520;  // "age "
        w2_sha256 = 32'h64696765;  // "dige"
        w3_sha256 = 32'h73748000;  // "st" + padding bit
        w15_sha256 = 32'h00000070;  // Length: 112 bits (14 bytes)
        
        run_test("Test Case 5: Message 'message digest'", 
                 256'hf7846f55cf23e14eebeab5b4e1550cad5b509e3348fbc4efa3a1413d393cb650);
        
        //========================================================================
        // Test Case 6: "abcdbcdecdefdefgefghfghighijhijkijkljklmklmnlmnomnopnopq"  
        // Expected: 248d6a61d20638b8e5c026930c3e6039a33ce45964ff2167f6ecedd419db06c1
        // Note: This is exactly 56 bytes = 448 bits, fits in one 512-bit block
        //========================================================================
        clear_message();
        w0_sha256 = 32'h61626364;  // "abcd"
        w1_sha256 = 32'h62636465;  // "bcde"
        w2_sha256 = 32'h63646566;  // "cdef"
        w3_sha256 = 32'h64656667;  // "defg"
        w4_sha256 = 32'h65666768;  // "efgh"
        w5_sha256 = 32'h66676869;  // "fghi"
        w6_sha256 = 32'h6768696a;  // "ghij"
        w7_sha256 = 32'h68696a6b;  // "hijk"
        w8_sha256 = 32'h696a6b6c;  // "ijkl"
        w9_sha256 = 32'h6a6b6c6d;  // "jklm"
        w10_sha256 = 32'h6b6c6d6e; // "klmn"
        w11_sha256 = 32'h6c6d6e6f; // "lmno"
        w12_sha256 = 32'h6d6e6f70; // "mnop"
        w13_sha256 = 32'h6e6f7071; // "nopq"
        w14_sha256 = 32'h80000000; // padding bit (56 bytes = 448 bits, so padding starts here)
        w15_sha256 = 32'h000001C0; // Length: 448 bits (56 bytes)
        
        run_test("Test Case 6: Long message", 
                 256'h248d6a61d20638b8e5c026930c3e6039a33ce45964ff2167f6ecedd419db06c1);
        
        //========================================================================
        // Display final results
        //========================================================================
        $display("\n=== Test Summary ===");
        $display("Total tests: %0d", total_tests);
        $display("Passed: %0d", passed_tests);
        $display("Failed: %0d", total_tests - passed_tests);
        
        if (passed_tests == total_tests) begin
            $display("✓ ALL TESTS PASSED!");
        end else begin
            $display("✗ Some tests failed!");
        end
        
        $display("Simulation finished at time: %0t", $time);
        
        // End simulation
        #100;
        $finish;
    end
    
    // Timeout watchdog (in case the design hangs)
    initial begin
        #50000; // 50,000 time units timeout (should be enough for all tests)
        $display("ERROR: Simulation timeout!");
        $finish;
    end

endmodule

build/sha256_test.vcd
$date
	Sat Aug  9 07:42:25 2025
$end
$version
	Icarus Verilog
$end
$timescale
	1ps
$end
$scope module SHA256tb $end
$var wire 256 ! sha256_result [255:0] $end
$var wire 1 " sha256_done $end
$var reg 32 # A_i [31:0] $end
$var reg 32 $ B_i [31:0] $end
$var reg 32 % C_i [31:0] $end
$var reg 32 & D_i [31:0] $end
$var reg 32 ' E_i [31:0] $end
$var reg 32 ( F_i [31:0] $end
$var reg 32 ) G_i [31:0] $end
$var reg 32 * H_i [31:0] $end
$var reg 1 + clk $end
$var reg 256 , expected_result [255:0] $end
$var reg 1 - reset $end
$var reg 1 . start_in $end
$var reg 32 / w0_sha256 [31:0] $end
$var reg 32 0 w10_sha256 [31:0] $end
$var reg 32 1 w11_sha256 [31:0] $end
$var reg 32 2 w12_sha256 [31:0] $end
$var reg 32 3 w13_sha256 [31:0] $end
$var reg 32 4 w14_sha256 [31:0] $end
$var reg 32 5 w15_sha256 [31:0] $end
$var reg 32 6 w1_sha256 [31:0] $end
$var reg 32 7 w2_sha256 [31:0] $end
$var reg 32 8 w3_sha256 [31:0] $end
$var reg 32 9 w4_sha256 [31:0] $end
$var reg 32 : w5_sha256 [31:0] $end
$var reg 32 ; w6_sha256 [31:0] $end
$var reg 32 < w7_sha256 [31:0] $end
$var reg 32 = w8_sha256 [31:0] $end
$var reg 32 > w9_sha256 [31:0] $end
$var integer 32 ? cycle_count [31:0] $end
$var integer 32 @ passed_tests [31:0] $end
$var integer 32 A total_tests [31:0] $end
$scope module uut $end
$var wire 32 B A_i [31:0] $end
$var wire 32 C B_i [31:0] $end
$var wire 32 D C_i [31:0] $end
$var wire 32 E D_i [31:0] $end
$var wire 32 F E_i [31:0] $end
$var wire 32 G F_i [31:0] $end
$var wire 32 H G_i [31:0] $end
$var wire 32 I H_i [31:0] $end
$var wire 1 + clk $end
$var wire 1 - reset $end
$var wire 1 . start_in $end
$var wire 32 J w0_sha256 [31:0] $end
$var wire 32 K w10_sha256 [31:0] $end
$var wire 32 L w11_sha256 [31:0] $end
$var wire 32 M w12_sha256 [31:0] $end
$var wire 32 N w13_sha256 [31:0] $end
$var wire 32 O w14_sha256 [31:0] $end
$var wire 32 P w15_sha256 [31:0] $end
$var wire 32 Q w1_sha256 [31:0] $end
$var wire 32 R w2_sha256 [31:0] $end
$var wire 32 S w3_sha256 [31:0] $end
$var wire 32 T w4_sha256 [31:0] $end
$var wire 32 U w5_sha256 [31:0] $end
$var wire 32 V w6_sha256 [31:0] $end
$var wire 32 W w7_sha256 [31:0] $end
$var wire 32 X w8_sha256 [31:0] $end
$var wire 32 Y w9_sha256 [31:0] $end
$var wire 32 Z T2 [31:0] $end
$var wire 32 [ T1 [31:0] $end
$var parameter 3 \ DONE $end
$var parameter 3 ] FINALIZE $end
$var parameter 32 ^ H0_INIT $end
$var parameter 32 _ H1_INIT $end
$var parameter 32 ` H2_INIT $end
$var parameter 32 a H3_INIT $end
$var parameter 32 b H4_INIT $end
$var parameter 32 c H5_INIT $end
$var parameter 32 d H6_INIT $end
$var parameter 32 e H7_INIT $end
$var parameter 3 f IDLE $end
$var parameter 3 g INIT $end
$var parameter 3 h PROCESS $end
$var reg 32 i H0 [31:0] $end
$var reg 32 j H1 [31:0] $end
$var reg 32 k H2 [31:0] $end
$var reg 32 l H3 [31:0] $end
$var reg 32 m H4 [31:0] $end
$var reg 32 n H5 [31:0] $end
$var reg 32 o H6 [31:0] $end
$var reg 32 p H7 [31:0] $end
$var reg 32 q W_current [31:0] $end
$var reg 32 r a [31:0] $end
$var reg 32 s b [31:0] $end
$var reg 32 t c [31:0] $end
$var reg 32 u d [31:0] $end
$var reg 32 v e [31:0] $end
$var reg 32 w f [31:0] $end
$var reg 32 x g [31:0] $end
$var reg 32 y h [31:0] $end
$var reg 7 z round_counter [6:0] $end
$var reg 1 " sha256_done $end
$var reg 256 { sha256_result [255:0] $end
$var reg 3 | state [2:0] $end
$scope function big_sigma0 $end
$var reg 32 } x [31:0] $end
$upscope $end
$scope function big_sigma1 $end
$var reg 32 ~ x [31:0] $end
$upscope $end
$scope function choice $end
$var reg 32 !" e [31:0] $end
$var reg 32 "" f [31:0] $end
$var reg 32 #" g [31:0] $end
$upscope $end
$scope function majority $end
$var reg 32 $" a [31:0] $end
$var reg 32 %" b [31:0] $end
$var reg 32 &" c [31:0] $end
$upscope $end
$scope function rotr $end
$var reg 5 '" n [4:0] $end
$var reg 32 (" x [31:0] $end
$upscope $end
$scope function small_sigma0 $end
$var reg 32 )" x [31:0] $end
$upscope $end
$scope function small_sigma1 $end
$var reg 32 *" x [31:0] $end
$upscope $end
$upscope $end
$scope task clear_message $end
$upscope $end
$scope task run_test $end
$var reg 256 +" expected [255:0] $end
$var reg 400 ," test_name [400:1] $end
$upscope $end
$upscope $end
$enddefinitions $end
$comment Show the parameter values. $end
$dumpall
b10 h
b1 g
b0 f
b1011011111000001100110100011001 e
b11111100000111101100110101011 d
b10011011000001010110100010001100 c
b1010001000011100101001001111111 b
b10100101010011111111010100111010 a
b111100011011101111001101110010 `
b10111011011001111010111010000101 _
b1101010000010011110011001100111 ^
b11 ]
b100 \
$end
#0
$dumpvars
bx ,"
bx +"
bx *"
bx )"
b0 ("
b11001 '"
b0 &"
b0 %"
b0 $"
b0 #"
b0 ""
b0 !"
b0 ~
b0 }
b0 |
b0 {
b0 z
b0 y
b0 x
b0 w
b0 v
b0 u
b0 t
b0 s
b0 r
b0 q
b0 p
b0 o
b0 n
b0 m
b0 l
b0 k
b0 j
b0 i
b1000010100010100010111110011000 [
b0 Z
b0 Y
b0 X
b0 W
b0 V
b0 U
b0 T
b0 S
b0 R
b0 Q
b0 P
b0 O
b0 N
b0 M
b0 L
b0 K
b0 J
b0 I
b0 H
b0 G
b0 F
b0 E
b0 D
b0 C
b0 B
b0 A
b0 @
b0 ?
b0 >
b0 =
b0 <
b0 ;
b0 :
b0 9
b0 8
b0 7
b0 6
b0 5
b0 4
b0 3
b0 2
b0 1
b0 0
b0 /
0.
0-
bx ,
0+
b0 *
b0 )
b0 (
b0 '
b0 &
b0 %
b0 $
b0 #
0"
b0 !
$end
#5000
1+
#10000
0+
1-
#15000
1+
#20000
0+
#25000
1+
#30000
0+
1.
b1011101001111000000101101011111110001111000000011100111111101010010000010100000101000000110111100101110110101110001000100010001110110000000000110110000110100011100101100001011101111010100111001011010000010000111111110110000111110010000000000001010110101101 ,
b1 A
b1011101001111000000101101011111110001111000000011100111111101010010000010100000101000000110111100101110110101110001000100010001110110000000000110110000110100011100101100001011101111010100111001011010000010000111111110110000111110010000000000001010110101101 +"
b101010001100101011100110111010000100000010000110110000101110011011001010010000000110001001110100010000001001101011001010111001101110011011000010110011101100101001000000010011101100001011000100110001100100111 ,"
b11000 5
b11000 P
b1100001011000100110001110000000 /
b1100001011000100110001110000000 J
#35000
b1 |
b1 ?
1+
#40000
0+
#45000
b1010001000011100101001001111111 ~
b11111100000111101100110101011 #"
b10011011000001010110100010001100 ""
b1010001000011100101001001111111 !"
b1010001000011100101001001111111 ("
b11001 '"
b1101010000010011110011001100111 }
b1000100100001001101011100101 Z
b111100011011101111001101110010 &"
b10111011011001111010111010000101 %"
b1101010000010011110011001100111 $"
b10 |
b1100001011000100110001110000000 q
b1010100110110100101000011101000 [
b1011011111000001100110100011001 y
b11111100000111101100110101011 x
b10011011000001010110100010001100 w
b1010001000011100101001001111111 v
b10100101010011111111010100111010 u
b111100011011101111001101110010 t
b10111011011001111010111010000101 s
b1101010000010011110011001100111 r
b1011011111000001100110100011001 p
b11111100000111101100110101011 o
b10011011000001010110100010001100 n
b1010001000011100101001001111111 m
b10100101010011111111010100111010 l
b111100011011101111001101110010 k
b10111011011001111010111010000101 j
b1101010000010011110011001100111 i
b10 ?
1+
#50000
0+
#55000
b1011101011010101110101111001101 }
b11110000010110101001110010110 Z
b10111011011001111010111010000101 &"
b1101010000010011110011001100111 %"
b1011101011010101110101111001101 $"
b1011101011010101110101111001101 ("
b10110 '"
b11111010001010100100011000100010 ~
b10011011000001010110100010001100 #"
b1010001000011100101001001111111 ""
b11111010001010100100011000100010 !"
b1 z
b0 q
b1011101011010101110101111001101 r
b1101010000010011110011001100111 s
b10111011011001111010111010000101 t
b111100011011101111001101110010 u
b11111010001010100100011000100010 v
b1010001000011100101001001111111 w
b10011011000001010110100010001100 x
b111100010111111000011000010111 [
b11111100000111101100110101011 y
b11 ?
1+
#60000
0+
#65000
b1011010011010101101100110101101 }
b10001011000000011011110001000001 Z
b1101010000010011110011001100111 &"
b1011101011010101110101111001101 %"
b1011010011010101101100110101101 $"
b1011010011010101101100110101101 ("
b10110 '"
b1111000110011100111100110001001 ~
b1010001000011100101001001111111 #"
b11111010001010100100011000100010 ""
b1111000110011100111100110001001 !"
b10 z
b1011010011010101101100110101101 r
b1011101011010101110101111001101 s
b1101010000010011110011001100111 t
b10111011011001111010111010000101 u
b1111000110011100111100110001001 v
b11111010001010100100011000100010 w
b1010001000011100101001001111111 x
b111101110000011000101101100110 [
b10011011000001010110100010001100 y
b100 ?
1+
#70000
0+
#75000
b11001000110000110100011110100111 }
b11010011110101101010001111101 Z
b1011101011010101110101111001101 &"
b1011010011010101101100110101101 %"
b11001000110000110100011110100111 $"
b11001000110000110100011110100111 ("
b10110 '"
b11111001001010010011100111101011 ~
b11111010001010100100011000100010 #"
b1111000110011100111100110001001 ""
b11111001001010010011100111101011 !"
b11 z
b11001000110000110100011110100111 r
b1011010011010101101100110101101 s
b1011101011010101110101111001101 t
b1101010000010011110011001100111 u
b11111001001010010011100111101011 v
b1111000110011100111100110001001 w
b11111010001010100100011000100010 x
b10111010110101100010000111101001 [
b1010001000011100101001001111111 y
b101 ?
1+
#80000
0+
#85000
b11010101010100001111011001100110 }
b11101111111011110001111110010 Z
b1011010011010101101100110101101 &"
b11001000110000110100011110100111 %"
b11010101010100001111011001100110 $"
b11010101010100001111011001100110 ("
b10110 '"
b100100111000000000100001010000 ~
b1111000110011100111100110001001 #"
b11111001001010010011100111101011 ""
b100100111000000000100001010000 !"
b100 z
b11010101010100001111011001100110 r
b11001000110000110100011110100111 s
b1011010011010101101100110101101 t
b1011101011010101110101111001101 u
b100100111000000000100001010000 v
b11111001001010010011100111101011 w
b1111000110011100111100110001001 x
b11100110010000101011011001111000 [
b11111010001010100100011000100010 y
b110 ?
1+
#90000
0+
#95000
b100010000001001101001101010 }
b10100011010101000001011110101 Z
b11001000110000110100011110100111 &"
b11010101010100001111011001100110 %"
b100010000001001101001101010 $"
b100010000001001101001101010 ("
b10110 '"
b1000011101011011010001001000101 ~
b11111001001010010011100111101011 #"
b100100111000000000100001010000 ""
b1000011101011011010001001000101 !"
b101 z
b100010000001001101001101010 r
b11010101010100001111011001100110 s
b11001000110000110100011110100111 t
b1011010011010101101100110101101 u
b1000011101011011010001001000101 v
b100100111000000000100001010000 w
b11111001001010010011100111101011 x
b10110110101111000011100000000 [
b1111000110011100111100110001001 y
b111 ?
1+
#100000
0+
#105000
b101011010000100000100111110101 }
b10010100111101010011100100110 Z
b11010101010100001111011001100110 &"
b100010000001001101001101010 %"
b101011010000100000100111110101 $"
b101011010000100000100111110101 ("
b10110 '"
b1110001010000100110000010101101 ~
b100100111000000000100001010000 #"
b1000011101011011010001001000101 ""
b1110001010000100110000010101101 !"
b110 z
b101011010000100000100111110101 r
b100010000001001101001101010 s
b11010101010100001111011001100110 t
b11001000110000110100011110100111 u
b1110001010000100110000010101101 v
b1000011101011011010001001000101 w
b100100111000000000100001010000 x
b11010010011001000101110001011010 [
b11111001001010010011100111101011 y
b1000 ?
1+
#110000
0+
